[
    {
        "lat": -27.470125,
        "lng": 153.019701
    },
    {
        "lat": -27.470198,
        "lng": 153.019726
    },
    {
        "lat": -27.470274,
        "lng": 153.019746
    },
    {
        "lat": -27.470354,
        "lng": 153.019779
    },
    {
        "lat": -27.470429,
        "lng": 153.019859
    },
    {
        "lat": -27.470444,
        "lng": 153.01993
    },
    {
        "lat": -27.47048,
        "lng": 153.020018
    },
    {
        "lat": -27.470529,
        "lng": 153.020032
    },
    {
        "lat": -27.470577,
        "lng": 153.020102
    },
    {
        "lat": -27.470595,
        "lng": 153.020135
    },
    {
        "lat": -27.47067,
        "lng": 153.020158
    },
    {
        "lat": -27.47069,
        "lng": 153.02016
    },
    {
        "lat": -27.47077,
        "lng": 153.020219
    },
    {
        "lat": -27.47077,
        "lng": 153.020254
    },
    {
        "lat": -27.470817,
        "lng": 153.020293
    },
    {
        "lat": -27.47087,
        "lng": 153.02032
    },
    {
        "lat": -27.470887,
        "lng": 153.02032
    },
    {
        "lat": -27.47095,
        "lng": 153.020373
    },
    {
        "lat": -27.47105,
        "lng": 153.020393
    },
    {
        "lat": -27.471088,
        "lng": 153.02042
    },
    {
        "lat": -27.471166,
        "lng": 153.020464
    },
    {
        "lat": -27.471219,
        "lng": 153.02052
    },
    {
        "lat": -27.471245,
        "lng": 153.020595
    },
    {
        "lat": -27.471271,
        "lng": 153.02062
    },
    {
        "lat": -27.471348,
        "lng": 153.020657
    },
    {
        "lat": -27.471445,
        "lng": 153.020666
    },
    {
        "lat": -27.471504,
        "lng": 153.020754
    },
    {
        "lat": -27.47158,
        "lng": 153.020841
    },
    {
        "lat": -27.471662,
        "lng": 153.020867
    },
    {
        "lat": -27.471726,
        "lng": 153.02093
    },
    {
        "lat": -27.471811,
        "lng": 153.020956
    },
    {
        "lat": -27.471879,
        "lng": 153.021048
    },
    {
        "lat": -27.471957,
        "lng": 153.021072
    }
]